Computer Architecture/CA1/Implementation.v
// Hossein Moradi 810803090
// Soroush Nasiri 810803098

module ProgramCounter (output_reg, input_reg, clk, rst);
    input clk, rst;
    input  [31:0] input_reg;
    output reg [31:0] output_reg;

    always @(posedge clk or posedge rst) begin
        if (rst)
            output_reg <= 32'b0;
        else
            output_reg <= input_reg;
    end
endmodule


module InstructionMemory (result, adr);
    input  [31:0] adr;
    output reg [31:0] result;

    always @(adr) begin
        result = 32'h00000013;
        case (adr)
            32'd0:   result = 32'h3E800913;
            32'd4:   result = 32'h00000413;
            32'd8:   result = 32'h00942293;
            32'd12:  result = 32'h04028A63;
            32'd16:  result = 32'h3E800913;
            32'd20:  result = 32'h00000493;
            32'd24:  result = 32'h0094A313;
            32'd28:  result = 32'h02030E63;
            32'd32:  result = 32'h00092383;
            32'd36:  result = 32'h00492E03;
            32'd40:  result = 32'h007E4863;
            32'd44:  result = 32'h00490913;
            32'd48:  result = 32'h00148493;
            32'd52:  result = 32'hFE5FF06F;
            32'd56:  result = 32'h00038EB3;
            32'd60:  result = 32'h000E03B3;
            32'd64:  result = 32'h000E8E33;
            32'd68:  result = 32'h00792023;
            32'd72:  result = 32'h01C92223;
            32'd76:  result = 32'h00490913;
            32'd80:  result = 32'h00148493;
            32'd84:  result = 32'hFC5FF06F;
            32'd88:  result = 32'h00140413;
            32'd92:  result = 32'hFADFF06F;
            32'd96:  result = 32'h3E800B13;
            32'd100: result = 32'h000B2B83;
            32'd104: result = 32'h004B2B83;
            32'd108: result = 32'h008B2B83;
            32'd112: result = 32'h00CB2B83;
            32'd116: result = 32'h010B2B83;
            32'd120: result = 32'h014B2B83;
            32'd124: result = 32'h018B2B83;
            32'd128: result = 32'h01CB2B83;
            32'd132: result = 32'h020B2B83;
            32'd136: result = 32'h024B2B83;
            32'd140: result = 32'h0000006F;
            default: result = 32'h00000013;
        endcase
    end
endmodule


module RegisterFile (rd1, rd2, rs1, rs2, rw, wd, we, clk);
    input  [4:0]  rs1, rs2, rw;
    input  [31:0] wd;
    input         we, clk;
    output [31:0] rd1, rd2;

    reg [31:0] regs [0:31];

    integer i;
    initial begin
        for (i = 0; i < 32; i = i + 1)
            regs[i] = 32'b0;
    end

    assign rd1 = (rs1 == 5'b0) ? 32'b0 : regs[rs1];
    assign rd2 = (rs2 == 5'b0) ? 32'b0 : regs[rs2];

    always @(posedge clk) begin
        if (we && (rw != 5'b0))
            regs[rw] <= wd;
    end
endmodule


module SimpleALU (Y, A, B);
    input  [31:0] A, B;
    output [31:0] Y;
    assign Y = A + B;
endmodule


module ALU (Y, zero, neg, A, B, ALUfunc);
    output reg [31:0] Y;
    output            zero, neg;
    input  [31:0]     A, B;
    input  [2:0]      ALUfunc;

    always @(A or B or ALUfunc) begin
        case (ALUfunc)
            3'd0: Y = A + B;
            3'd1: Y = A + (~B) + 1;
            3'd2: Y = A & B;
            3'd3: Y = A | B;
            3'd4: Y = A ^ B;
            3'd5: Y = ($signed(A) < $signed(B)) ? 32'b1 : 32'b0;
            default: Y = 32'b0;
        endcase
    end

    assign zero = (Y == 32'b0);
    assign neg  = Y[31];
endmodule


module DataMemory (rd, adr, wd, we, clk);
    output [31:0] rd;
    input  [31:0] adr, wd;
    input         we, clk;

    localparam MEM_WORDS = 1 << 12;
    reg [31:0] memory [0 : MEM_WORDS-1];

    assign rd = memory[adr[13:2]];

    always @(posedge clk) begin
        if (we)
            memory[adr[13:2]] <= wd;
    end

    integer k;
    initial begin
        for (k = 0; k < MEM_WORDS; k = k + 1)
            memory[k] = 32'b0;
        memory[250] = 32'h0000004A;
        memory[251] = 32'hFFFFFFF4;
        memory[252] = 32'h0000002B;
        memory[253] = 32'hFFFFFFE1;
        memory[254] = 32'hFFFFFFF1;
        memory[255] = 32'h0000000A;
        memory[256] = 32'h00000009;
        memory[257] = 32'h00000012;
        memory[258] = 32'h0000000D;
        memory[259] = 32'hFFFFFFEB;
    end
endmodule


module ImmediateExtention (result, imm, Immsrc);
    output reg [31:0] result;
    input      [24:0] imm;
    input      [1:0]  Immsrc;

    always @(imm or Immsrc) begin
        case (Immsrc)
            2'b00: result = {{20{imm[24]}}, imm[24:13]};
            2'b01: result = {{20{imm[24]}}, imm[24:18], imm[4:0]};
            2'b10: result = {{19{imm[24]}}, imm[24], imm[0], imm[23:18], imm[4:1], 1'b0};
            2'b11: result = {{11{imm[24]}}, imm[24], imm[12:5], imm[13], imm[23:14], 1'b0};
            default: result = 32'b0;
        endcase
    end
endmodule


module ControlUnit (
    resultSrc,
    memWrite,
    aluSrc,
    aluFunc,
    regWrite,
    immSrc,
    pcSrc,
    zero, neg,
    opcode,
    func3,
    func7
);
    input        zero, neg;
    input  [6:0] opcode;
    input  [2:0] func3;
    input  [6:0] func7;

    output [1:0] resultSrc;
    output       memWrite, aluSrc, regWrite;
    output reg [2:0] aluFunc;
    output [1:0] immSrc;
    output [1:0] pcSrc;

    reg [1:0] aluOp;

    always @(opcode) begin
        case (opcode)
            7'd51:  aluOp = 2'b10;
            7'd19:  aluOp = 2'b11;
            7'd3:   aluOp = 2'b00;
            7'd35:  aluOp = 2'b00;
            7'd103: aluOp = 2'b00;
            7'd99:  aluOp = 2'b01;
            7'd111: aluOp = 2'b00;
            default: aluOp = 2'b00;
        endcase
    end

    always @(aluOp or func3 or func7) begin
        case (aluOp)
            2'b00: aluFunc = 3'd0;
            2'b01: aluFunc = 3'd1;
            2'b10: begin
                case ({func7, func3})
                    {7'd0,  3'd0}: aluFunc = 3'd0;
                    {7'd32, 3'd0}: aluFunc = 3'd1;
                    {7'd0,  3'd7}: aluFunc = 3'd2;
                    {7'd0,  3'd6}: aluFunc = 3'd3;
                    {7'd0,  3'd4}: aluFunc = 3'd4;
                    {7'd0,  3'd2}: aluFunc = 3'd5;
                    default:       aluFunc = 3'd0;
                endcase
            end
            2'b11: begin
                case (func3)
                    3'd0: aluFunc = 3'd0;
                    3'd6: aluFunc = 3'd3;
                    3'd4: aluFunc = 3'd4;
                    3'd2: aluFunc = 3'd5;
                    default: aluFunc = 3'd0;
                endcase
            end
            default: aluFunc = 3'd0;
        endcase
    end

    wire branch_taken;
    assign branch_taken =
        (func3 == 3'b000 &&  zero)          |
        (func3 == 3'b001 && ~zero)          |
        (func3 == 3'b100 &&  neg && ~zero)  |
        (func3 == 3'b101 && (~neg || zero));

    assign pcSrc =
        (opcode == 7'd103)                ? 2'b10 :
        (opcode == 7'd111)                ? 2'b01 :
        (opcode == 7'd99 && branch_taken) ? 2'b01 :
                                            2'b00;

    assign resultSrc =
        (opcode == 7'd3)                        ? 2'b01 :
        (opcode == 7'd111 || opcode == 7'd103)  ? 2'b10 :
                                                  2'b00;

    assign memWrite = (opcode == 7'd35);

    assign aluSrc = (opcode == 7'd51 || opcode == 7'd99) ? 1'b0 : 1'b1;

    assign immSrc =
        (opcode == 7'd19 || opcode == 7'd3 || opcode == 7'd103) ? 2'b00 :
        (opcode == 7'd35)                                        ? 2'b01 :
        (opcode == 7'd99)                                        ? 2'b10 :
        (opcode == 7'd111)                                       ? 2'b11 :
                                                                   2'b00;

    assign regWrite =
        (opcode == 7'd51  ||
         opcode == 7'd19  ||
         opcode == 7'd3   ||
         opcode == 7'd111 ||
         opcode == 7'd103);

endmodule

Computer Architecture/CA1/RiscV.v
// Soroush Nasiri 810803098
// Hossein Moradi 810803090

module RiscV (result, clk, rst);
    input        clk, rst;
    output [31:0] result;

    wire [31:0] pcOut;
    wire [31:0] pcNext;
    wire [31:0] pc4;
    wire [31:0] pcImm;
    wire [31:0] instr;
    wire [31:0] rd1;
    wire [31:0] rd2;
    wire [31:0] immExt;
    wire [31:0] aluB;
    wire [31:0] aluOut;
    wire [31:0] memOut;
    wire [31:0] wdReg;
    wire zero, neg;
    wire [1:0]  pcSrc;
    wire [1:0]  resultSrc;
    wire [1:0]  immSrc;
    wire [2:0]  aluFunc;
    wire memWrite, regWrite, aluSrc;

    ProgramCounter PC (
        .output_reg (pcOut),
        .input_reg  (pcNext),
        .clk        (clk),
        .rst        (rst)
    );

    InstructionMemory IM (
        .result (instr),
        .adr    (pcOut)
    );

    SimpleALU pcPlus4 (
        .Y (pc4),
        .A (pcOut),
        .B (32'd4)
    );

    SimpleALU pcPlusImm (
        .Y (pcImm),
        .A (pcOut),
        .B (immExt)
    );

    assign pcNext = (pcSrc == 2'b10) ? aluOut :
                    (pcSrc == 2'b01) ? pcImm  :
                                       pc4;

    RegisterFile RF (
        .rd1 (rd1),
        .rd2 (rd2),
        .rs1 (instr[19:15]),
        .rs2 (instr[24:20]),
        .rw  (instr[11:7]),
        .wd  (wdReg),
        .we  (regWrite),
        .clk (clk)
    );

    ImmediateExtention ImmExt (
        .result  (immExt),
        .imm     (instr[31:7]),
        .Immsrc  (immSrc)
    );

    assign aluB = aluSrc ? immExt : rd2;

    ALU MainALU (
        .Y       (aluOut),
        .zero    (zero),
        .neg     (neg),
        .A       (rd1),
        .B       (aluB),
        .ALUfunc (aluFunc)
    );

    DataMemory DM (
        .rd  (memOut),
        .adr (aluOut),
        .wd  (rd2),
        .we  (memWrite),
        .clk (clk)
    );

    assign wdReg = (resultSrc == 2'b01) ? memOut :
                   (resultSrc == 2'b10) ? pc4    :
                                          aluOut;

    ControlUnit CU (
        .resultSrc (resultSrc),
        .memWrite  (memWrite),
        .aluSrc    (aluSrc),
        .aluFunc   (aluFunc),
        .regWrite  (regWrite),
        .immSrc    (immSrc),
        .pcSrc     (pcSrc),
        .zero      (zero),
        .neg       (neg),
        .opcode    (instr[6:0]),
        .func3     (instr[14:12]),
        .func7     (instr[31:25])
    );

    assign result = wdReg;

endmodule

Computer Architecture/CA1/RiscV_TB.v
// Soroush Nasiri 810803098
// Hossein Moradi 810803090

module RiscV_TB ();
    reg clk, rst;
    wire [31:0]Res;
    RiscV risc5(Res, clk, rst);
    initial begin

        #5 rst = 1;
        #20 rst = 0;
        #30 clk = 0;
        repeat (20000) #10 clk = ~clk;
    end
endmodule

Computer Architecture/CA1/CA1/riscv_waveform.vcd
$date
	Tue May 19 12:56:24 2026
$end
$version
	Icarus Verilog
$end
$timescale
	1s
$end
$scope module RiscV_TB $end
$var wire 32 ! Res [31:0] $end
$var reg 1 " clk $end
$var reg 1 # rst $end
$scope module risc5 $end
$var wire 1 " clk $end
$var wire 32 $ result [31:0] $end
$var wire 1 # rst $end
$var wire 1 % zero $end
$var wire 32 & wdReg [31:0] $end
$var wire 2 ' resultSrc [1:0] $end
$var wire 1 ( regWrite $end
$var wire 32 ) rd2 [31:0] $end
$var wire 32 * rd1 [31:0] $end
$var wire 2 + pcSrc [1:0] $end
$var wire 32 , pcOut [31:0] $end
$var wire 32 - pcNext [31:0] $end
$var wire 32 . pcImm [31:0] $end
$var wire 32 / pc4 [31:0] $end
$var wire 1 0 neg $end
$var wire 1 1 memWrite $end
$var wire 32 2 memOut [31:0] $end
$var wire 32 3 instr [31:0] $end
$var wire 2 4 immSrc [1:0] $end
$var wire 32 5 immExt [31:0] $end
$var wire 1 6 aluSrc $end
$var wire 32 7 aluOut [31:0] $end
$var wire 3 8 aluFunc [2:0] $end
$var wire 32 9 aluB [31:0] $end
$scope module CU $end
$var wire 1 : branch_taken $end
$var wire 3 ; func3 [2:0] $end
$var wire 7 < func7 [6:0] $end
$var wire 7 = opcode [6:0] $end
$var wire 1 ( regWrite $end
$var wire 1 % zero $end
$var wire 2 > resultSrc [1:0] $end
$var wire 2 ? pcSrc [1:0] $end
$var wire 1 0 neg $end
$var wire 1 1 memWrite $end
$var wire 2 @ immSrc [1:0] $end
$var wire 1 6 aluSrc $end
$var reg 3 A aluFunc [2:0] $end
$var reg 2 B aluOp [1:0] $end
$upscope $end
$scope module DM $end
$var wire 1 " clk $end
$var wire 32 C rd [31:0] $end
$var wire 1 1 we $end
$var wire 32 D wd [31:0] $end
$var wire 32 E adr [31:0] $end
$var parameter 44 F MEM_WORDS $end
$var integer 32 G k [31:0] $end
$upscope $end
$scope module IM $end
$var wire 32 H adr [31:0] $end
$var reg 32 I result [31:0] $end
$upscope $end
$scope module ImmExt $end
$var wire 2 J Immsrc [1:0] $end
$var wire 25 K imm [24:0] $end
$var reg 32 L result [31:0] $end
$upscope $end
$scope module MainALU $end
$var wire 3 M ALUfunc [2:0] $end
$var wire 32 N B [31:0] $end
$var wire 1 % zero $end
$var wire 1 0 neg $end
$var wire 32 O A [31:0] $end
$var reg 32 P Y [31:0] $end
$upscope $end
$scope module PC $end
$var wire 1 " clk $end
$var wire 32 Q input_reg [31:0] $end
$var wire 1 # rst $end
$var reg 32 R output_reg [31:0] $end
$upscope $end
$scope module RF $end
$var wire 1 " clk $end
$var wire 5 S rs1 [4:0] $end
$var wire 5 T rs2 [4:0] $end
$var wire 5 U rw [4:0] $end
$var wire 32 V wd [31:0] $end
$var wire 1 ( we $end
$var wire 32 W rd2 [31:0] $end
$var wire 32 X rd1 [31:0] $end
$var integer 32 Y i [31:0] $end
$upscope $end
$scope module pcPlus4 $end
$var wire 32 Z A [31:0] $end
$var wire 32 [ B [31:0] $end
$var wire 32 \ Y [31:0] $end
$upscope $end
$scope module pcPlusImm $end
$var wire 32 ] A [31:0] $end
$var wire 32 ^ B [31:0] $end
$var wire 32 _ Y [31:0] $end
$upscope $end
$upscope $end
$upscope $end
$enddefinitions $end
$comment Show the parameter values. $end
$dumpall
b1000000000000 F
$end
#0
$dumpvars
bx _
b0 ^
bx ]
bx \
b100 [
bx Z
b100000 Y
bx X
bx W
bx V
bx U
bx T
bx S
bx R
bx Q
bx P
bx O
bx N
bx M
b0 L
bx K
bx J
bx I
bx H
b1000000000000 G
bx E
bx D
bx C
bx B
bx A
bx @
bx ?
bx >
bx =
bx <
bx ;
x:
bx 9
bx 8
bx 7
x6
b0 5
bx 4
bx 3
bx 2
x1
x0
bx /
bx .
bx -
bx ,
bx +
bx *
bx )
x(
bx '
bx &
x%
bx $
x#
x"
bx !
$end
#5
0:
b1001010 2
b1001010 C
b1111101000 !
b1111101000 $
b1111101000 &
b1111101000 V
1(
00
b1111101000 5
b1111101000 L
b1111101000 ^
0%
b1111101000 7
b1111101000 E
b1111101000 P
b100 -
b100 Q
16
b0 4
b0 @
b0 J
b1111101000 9
b1111101000 N
b0 8
b0 A
b0 M
b11 B
b0 +
b0 ?
b0 '
b0 >
b0 )
b0 D
b0 W
b0 *
b0 O
b0 X
b11111 <
b0 ;
01
b10011 =
b11111010000000000010010 K
b10010 U
b1000 T
b0 S
b111110100000000000100100010011 3
b111110100000000000100100010011 I
b100 /
b100 \
b1111101000 .
b1111101000 _
b0 ,
b0 H
b0 R
b0 Z
b0 ]
1#
#25
0#
#55
0"
#65
1:
b0 2
b0 C
b0 !
b0 $
b0 &
b0 V
1%
b0 7
b0 E
b0 P
b0 9
b0 N
b0 5
b0 L
b0 ^
b1000 -
b1000 Q
b0 <
b1000 K
b1000 U
b0 T
b10000010011 3
b10000010011 I
b1000 /
b1000 \
b100 .
b100 _
b100 ,
b100 H
b100 R
b100 Z
b100 ]
1"
#75
0"
#85
b1 !
b1 $
b1 &
b1 V
0:
0%
b1 7
b1 E
b1 P
b1001 9
b1001 N
b101 8
b101 A
b101 M
b1001 5
b1001 L
b1001 ^
b1100 -
b1100 Q
b10 ;
b1001 T
b1000 S
b10010100001000101 K
b101 U
b100101000010001010010011 3
b100101000010001010010011 I
b1100 /
b1100 \
b10001 .
b10001 _
b1000 ,
b1000 H
b1000 R
b1000 Z
b1000 ]
1"
#95
0"
#105
0(
b1 !
b1 $
b1 &
b1 V
b10 4
b10 @
b10 J
06
b1 7
b1 E
b1 P
b0 9
b0 N
b1 *
b1 O
b1 X
b1 B
b1 8
b1 A
b1 M
b1010100 5
b1010100 L
b1010100 ^
b10000 -
b10000 Q
b10 <
b1100011 =
b0 ;
b10000000010100010100 K
b10100 U
b0 T
b101 S
b100000000101000101001100011 3
b100000000101000101001100011 I
b10000 /
b10000 \
b1100000 .
b1100000 _
b1100 ,
b1100 H
b1100 R
b1100 Z
b1100 ]
1"
#115
0"
#125
b1001010 2
b1001010 C
0:
1(
b1111101000 !
b1111101000 $
b1111101000 &
b1111101000 V
b1111101000 9
b1111101000 N
b0 4
b0 @
b0 J
16
0%
b1111101000 7
b1111101000 E
b1111101000 P
b0 8
b0 A
b0 M
b11 B
b1111101000 5
b1111101000 L
b1111101000 ^
b0 *
b0 O
b0 X
b10100 -
b10100 Q
b1000 T
b11111 <
b10011 =
b11111010000000000010010 K
b10010 U
b0 S
b111110100000000000100100010011 3
b111110100000000000100100010011 I
b10100 /
b10100 \
b1111111000 .
b1111111000 _
b10000 ,
b10000 H
b10000 R
b10000 Z
b10000 ]
1"
#135
0"
#145
1:
b0 2
b0 C
b0 !
b0 $
b0 &
b0 V
1%
b0 7
b0 E
b0 P
b0 9
b0 N
b0 5
b0 L
b0 ^
b11000 -
b11000 Q
b0 <
b1001 K
b1001 U
b0 T
b10010010011 3
b10010010011 I
b11000 /
b11000 \
b10100 .
b10100 _
b10100 ,
b10100 H
b10100 R
b10100 Z
b10100 ]
1"
#155
0"
#165
b1 !
b1 $
b1 &
b1 V
0:
0%
b1 7
b1 E
b1 P
b1001 9
b1001 N
b101 8
b101 A
b101 M
b1001 5
b1001 L
b1001 ^
b11100 -
b11100 Q
b10 ;
b1001 T
b1001 S
b10010100101000110 K
b110 U
b100101001010001100010011 3
b100101001010001100010011 I
b11100 /
b11100 \
b100001 .
b100001 _
b11000 ,
b11000 H
b11000 R
b11000 Z
b11000 ]
1"
#175
0"
#185
0(
b1 !
b1 $
b1 &
b1 V
b10 4
b10 @
b10 J
06
b1 7
b1 E
b1 P
b0 9
b0 N
b1 *
b1 O
b1 X
b1 B
b1 8
b1 A
b1 M
b111100 5
b111100 L
b111100 ^
b100000 -
b100000 Q
b1 <
b1100011 =
b0 ;
b1000000011000011100 K
b11100 U
b0 T
b110 S
b10000000110000111001100011 3
b10000000110000111001100011 I
b100000 /
b100000 \
b1011000 .
b1011000 _
b11100 ,
b11100 H
b11100 R
b11100 Z
b11100 ]
1"
#195
0"
#205
b1001010 2
b1001010 C
b0 9
b0 N
b0 4
b0 @
b0 J
1(
b1111101000 7
b1111101000 E
b1111101000 P
b1001010 !
b1001010 $
b1001010 &
b1001010 V
16
b1111101000 *
b1111101000 O
b1111101000 X
b0 8
b0 A
b0 M
b0 B
b1 '
b1 >
b0 5
b0 L
b0 ^
b100100 -
b100100 Q
b10 ;
b0 <
b11 =
b1001001000111 K
b111 U
b10010 S
b10010010001110000011 3
b10010010001110000011 I
b100100 /
b100100 \
b100000 .
b100000 _
b100000 ,
b100000 H
b100000 R
b100000 Z
b100000 ]
1"
#215
0"
#225
b11111111111111111111111111110100 !
b11111111111111111111111111110100 $
b11111111111111111111111111110100 &
b11111111111111111111111111110100 V
b11111111111111111111111111110100 2
b11111111111111111111111111110100 C
b1111101100 7
b1111101100 E
b1111101100 P
b100 9
b100 N
b100 5
b100 L
b100 ^
b101000 -
b101000 Q
b100 T
b1001001001011100 K
b11100 U
b10010010010111000000011 3
b10010010010111000000011 I
b101000 /
b101000 \
b101000 .
b101000 _
b100100 ,
b100100 H
b100100 R
b100100 Z
b100100 ]
1"
#235
0"
#245
b1 +
b1 ?
1:
b0 2
b0 C
10
b10 4
b10 @
b10 J
0(
b11111111111111111111111110101010 7
b11111111111111111111111110101010 E
b11111111111111111111111110101010 P
b11111111111111111111111110101010 !
b11111111111111111111111110101010 $
b11111111111111111111111110101010 &
b11111111111111111111111110101010 V
06
b1001010 9
b1001010 N
b1001010 )
b1001010 D
b1001010 W
b11111111111111111111111111110100 *
b11111111111111111111111111110100 O
b11111111111111111111111111110100 X
b1 8
b1 A
b1 M
b1 B
b0 '
b0 >
b10000 5
b10000 L
b10000 ^
b111000 -
b111000 Q
b100 ;
b1100011 =
b1111110010010000 K
b10000 U
b111 T
b11100 S
b11111100100100001100011 3
b11111100100100001100011 I
b101100 /
b101100 \
b111000 .
b111000 _
b101000 ,
b101000 H
b101000 R
b101000 Z
b101000 ]
1"
#255
0"
#265
b1001010 !
b1001010 $
b1001010 &
b1001010 V
0:
b0 +
b0 ?
1(
00
b0 4
b0 @
b0 J
b1001010 7
b1001010 E
b1001010 P
b0 9
b0 N
b1001010 *
b1001010 O
b1001010 X
b0 8
b0 A
b0 M
b10 B
b0 5
b0 L
b0 ^
b0 )
b0 D
b0 W
b111100 -
b111100 Q
b0 ;
b110011 =
b11100011101 K
b11101 U
b0 T
b111 S
b111000111010110011 3
b111000111010110011 I
b111100 /
b111100 \
b111000 .
b111000 _
b111000 ,
b111000 H
b111000 R
b111000 Z
b111000 ]
1"
#275
0"
#285
b11111111111111111111111111110100 !
b11111111111111111111111111110100 $
b11111111111111111111111111110100 &
b11111111111111111111111111110100 V
10
b11111111111111111111111111110100 7
b11111111111111111111111111110100 E
b11111111111111111111111111110100 P
b11111111111111111111111111110100 *
b11111111111111111111111111110100 O
b11111111111111111111111111110100 X
b1000000 -
b1000000 Q
b1110000000111 K
b111 U
b11100 S
b11100000001110110011 3
b11100000001110110011 I
b1000000 /
b1000000 \
b111100 .
b111100 _
b111100 ,
b111100 H
b111100 R
b111100 Z
b111100 ]
1"
#295
0"
#305
b1001010 !
b1001010 $
b1001010 &
b1001010 V
00
b1001010 7
b1001010 E
b1001010 P
b1001010 *
b1001010 O
b1001010 X
b1000100 -
b1000100 Q
b1110100011100 K
b11100 U
b11101 S
b11101000111000110011 3
b11101000111000110011 I
b1000100 /
b1000100 \
b1000000 .
b1000000 _
b1000000 ,
b1000000 H
b1000000 R
b1000000 Z
b1000000 ]
1"
#315
0"
#325
b1001010 2
b1001010 C
b1111101000 !
b1111101000 $
b1111101000 &
b1111101000 V
0(
b1111101000 7
b1111101000 E
b1111101000 P
b0 9
b0 N
16
b1 4
b1 @
b1 J
b1111101000 *
b1111101000 O
b1111101000 X
b11111111111111111111111111110100 )
b11111111111111111111111111110100 D
b11111111111111111111111111110100 W
b0 B
b0 5
b0 L
b0 ^
b1001000 -
b1001000 Q
b10 ;
b111 T
11
b100011 =
b1111001001000000 K
b0 U
b10010 S
b11110010010000000100011 3
b11110010010000000100011 I
b1001000 /
b1001000 \
b1000100 .
b1000100 _
b1000100 ,
b1000100 H
b1000100 R
b1000100 Z
b1000100 ]
1"
#335
0"
#345
b1111101100 !
b1111101100 $
b1111101100 &
b1111101100 V
b1111101100 7
b1111101100 E
b1111101100 P
b100 9
b100 N
b1001010 )
b1001010 D
b1001010 W
b100 5
b100 L
b100 ^
b1001100 -
b1001100 Q
b100 U
b111001001001000100 K
b11100 T
b1110010010010001000100011 3
b1110010010010001000100011 I
b11111111111111111111111111110100 2
b11111111111111111111111111110100 C
b1001100 /
b1001100 \
b1001100 .
b1001100 _
b1001000 ,
b1001000 H
b1001000 R
b1001000 Z
b1001000 ]
1"
#355
0"
#365
b1111101100 !
b1111101100 $
b1111101100 &
b1111101100 V
1(
b1111101100 7
b1111101100 E
b1111101100 P
b0 4
b0 @
b0 J
b100 9
b100 N
b0 )
b0 D
b0 W
b11 B
b100 5
b100 L
b100 ^
b1010000 -
b1010000 Q
b0 ;
01
b10011 =
b1001001000010010 K
b10010 U
b100 T
b10010010000100100010011 3
b10010010000100100010011 I
b1001010 2
b1001010 C
b1010000 /
b1010000 \
b1010000 .
b1010000 _
b1001100 ,
b1001100 H
b1001100 R
b1001100 Z
b1001100 ]
1"
#375
0"
#385
b0 2
b0 C
b1 !
b1 $
b1 &
b1 V
b1 9
b1 N
b1 5
b1 L
b1 ^
b1 7
b1 E
b1 P
b1010100 -
b1010100 Q
b10100100001001 K
b1001 U
b1 T
b1001 S
b0 *
b0 O
b0 X
b101001000010010010011 3
b101001000010010010011 I
b1010100 /
b1010100 \
b1010001 .
b1010001 _
b1010000 ,
b1010000 H
b1010000 R
b1010000 Z
b1010000 ]
1"
#395
0"
#405
10
b10 '
b10 >
b11 4
b11 @
b11 J
b1011000 !
b1011000 $
b1011000 &
b1011000 V
b1 +
b1 ?
b11111111111111111111111111000100 9
b11111111111111111111111111000100 N
b1 )
b1 D
b1 W
b0 B
b11111111111111111111111111000100 5
b11111111111111111111111111000100 L
b11111111111111111111111111000100 ^
b11111111111111111111111111000100 7
b11111111111111111111111111000100 E
b11111111111111111111111111000100 P
b11000 -
b11000 Q
b1111110 <
b111 ;
b1101111 =
b1111110001011111111100000 K
b0 U
b101 T
b11111 S
b0 *
b0 O
b0 X
b11111100010111111111000001101111 3
b11111100010111111111000001101111 I
b1011000 /
b1011000 \
b11000 .
b11000 _
b1010100 ,
b1010100 H
b1010100 R
b1010100 Z
b1010100 ]
1"
#415
0"
#425
00
b0 '
b0 >
b0 4
b0 @
b0 J
b1 7
b1 E
b1 P
b0 +
b0 ?
1(
b1001 9
b1001 N
b1 *
b1 O
b1 X
b101 8
b101 A
b101 M
b11 B
b1001 5
b1001 L
b1001 ^
b1 !
b1 $
b1 &
b1 V
b11100 -
b11100 Q
b110 U
b0 <
b10 ;
b10011 =
b10010100101000110 K
b1001 T
b1001 S
b100101001010001100010011 3
b100101001010001100010011 I
b11100 /
b11100 \
b100001 .
b100001 _
b11000 ,
b11000 H
b11000 R
b11000 Z
b11000 ]
1"
#435
0"
#445
0(
b1 !
b1 $
b1 &
b1 V
b10 4
b10 @
b10 J
06
b1 7
b1 E
b1 P
b0 9
b0 N
b1 B
b1 8
b1 A
b1 M
b111100 5
b111100 L
b111100 ^
b0 )
b0 D
b0 W
b100000 -
b100000 Q
b1 <
b1100011 =
b0 ;
b1000000011000011100 K
b11100 U
b0 T
b110 S
b10000000110000111001100011 3
b10000000110000111001100011 I
b100000 /
b100000 \
b1011000 .
b1011000 _
b11100 ,
b11100 H
b11100 R
b11100 Z
b11100 ]
1"
#455
0"
#465
b1001010 2
b1001010 C
b0 9
b0 N
b0 4
b0 @
b0 J
1(
b1111101100 7
b1111101100 E
b1111101100 P
b1001010 !
b1001010 $
b1001010 &
b1001010 V
16
b1111101100 *
b1111101100 O
b1111101100 X
b0 8
b0 A
b0 M
b0 B
b1 '
b1 >
b0 5
b0 L
b0 ^
b100100 -
b100100 Q
b10 ;
b0 <
b11 =
b1001001000111 K
b111 U
b10010 S
b10010010001110000011 3
b10010010001110000011 I
b100100 /
b100100 \
b100000 .
b100000 _
b100000 ,
b100000 H
b100000 R
b100000 Z
b100000 ]
1"
#475
0"
#485
b101011 !
b101011 $
b101011 &
b101011 V
b101011 2
b101011 C
b1111110000 7
b1111110000 E
b1111110000 P
b100 9
b100 N
b100 5
b100 L
b100 ^
b101000 -
b101000 Q
b100 T
b1001001001011100 K
b11100 U
b10010010010111000000011 3
b10010010010111000000011 I
b101000 /
b101000 \
b101000 .
b101000 _
b100100 ,
b100100 H
b100100 R
b100100 Z
b100100 ]
1"
#495
0"
#505
b1 +
b1 ?
1:
10
b0 2
b0 C
b10 4
b10 @
b10 J
0(
b11111111111111111111111111100001 7
b11111111111111111111111111100001 E
b11111111111111111111111111100001 P
b11111111111111111111111111100001 !
b11111111111111111111111111100001 $
b11111111111111111111111111100001 &
b11111111111111111111111111100001 V
06
b1001010 9
b1001010 N
b1001010 )
b1001010 D
b1001010 W
b101011 *
b101011 O
b101011 X
b1 8
b1 A
b1 M
b1 B
b0 '
b0 >
b10000 5
b10000 L
b10000 ^
b111000 -
b111000 Q
b100 ;
b1100011 =
b1111110010010000 K
b10000 U
b111 T
b11100 S
b11111100100100001100011 3
b11111100100100001100011 I
b101100 /
b101100 \
b111000 .
b111000 _
b101000 ,
b101000 H
b101000 R
b101000 Z
b101000 ]
1"
#515
0"
#525
b1001010 !
b1001010 $
b1001010 &
b1001010 V
0:
b0 +
b0 ?
1(
00
b0 4
b0 @
b0 J
b1001010 7
b1001010 E
b1001010 P
b0 9
b0 N
b1001010 *
b1001010 O
b1001010 X
b0 8
b0 A
b0 M
b10 B
b0 5
b0 L
b0 ^
b0 )
b0 D
b0 W
b111100 -
b111100 Q
b0 ;
b110011 =
b11100011101 K
b11101 U
b0 T
b111 S
b111000111010110011 3
b111000111010110011 I
b111100 /
b111100 \
b111000 .
b111000 _
b111000 ,
b111000 H
b111000 R
b111000 Z
b111000 ]
1"
#535
0"
#545
b101011 !
b101011 $
b101011 &
b101011 V
b101011 7
b101011 E
b101011 P
b101011 *
b101011 O
b101011 X
b1000000 -
b1000000 Q
b1110000000111 K
b111 U
b11100 S
b11100000001110110011 3
b11100000001110110011 I
b1000000 /
b1000000 \
b111100 .
b111100 _
b111100 ,
b111100 H
b111100 R
b111100 Z
b111100 ]
1"
#555
0"
#565
b1001010 !
b1001010 $
b1001010 &
b1001010 V
b1001010 7
b1001010 E
b1001010 P
b1001010 *
b1001010 O
b1001010 X
b1000100 -
b1000100 Q
b1110100011100 K
b11100 U
b11101 S
b11101000111000110011 3
b11101000111000110011 I
b1000100 /
b1000100 \
b1000000 .
b1000000 _
b1000000 ,
b1000000 H
b1000000 R
b1000000 Z
b1000000 ]
1"
#575
0"
#585
b1001010 2
b1001010 C
b1111101100 !
b1111101100 $
b1111101100 &
b1111101100 V
0(
b1111101100 7
b1111101100 E
b1111101100 P
b0 9
b0 N
16
b1 4
b1 @
b1 J
b1111101100 *
b1111101100 O
b1111101100 X
b101011 )
b101011 D
b101011 W
b0 B
b0 5
b0 L
b0 ^
b1001000 -
b1001000 Q
b10 ;
b111 T
11
b100011 =
b1111001001000000 K
b0 U
b10010 S
b11110010010000000100011 3
b11110010010000000100011 I
b1001000 /
b1001000 \
b1000100 .
b1000100 _
b1000100 ,
b1000100 H
b1000100 R
b1000100 Z
b1000100 ]
1"
#595
0"
